ProcessEntropy/CrossEntropy.py
ProcessEntropy/CrossEntropyPythonOnly.py
ProcessEntropy/Predictability.py
ProcessEntropy/Preprocessing.py
ProcessEntropy/SelfEntropy.py
ProcessEntropy/SelfEntropyPythonOnly.py
ProcessEntropy/__init__.py
ProcessEntropy-1.1.2.dev0.dist-info/LICENSE
ProcessEntropy-1.1.2.dev0.dist-info/METADATA
ProcessEntropy-1.1.2.dev0.dist-info/WHEEL
ProcessEntropy-1.1.2.dev0.dist-info/top_level.txt
ProcessEntropy-1.1.2.dev0.dist-info/RECORD
