Metadata-Version: 2.1
Name: ProcessEntropy
Version: 1.1.2.dev0
Summary: A toolkit for calculating sequence entropy and informantion flow quickly. With specific applications to tweets.
Home-page: https://github.com/tobinsouth/ProcessEntropy
Author: Tobin South
License: MIT license
License-File: LICENSE
Requires-Dist: numpy
Requires-Dist: numba
Requires-Dist: nltk
Requires-Dist: LCSFinder
